simplyphi_valuation
