Metadata-Version: 2.1
Name: simplyphi-valuation
Version: 0.2
Summary: A valuation tool for real estate and property management.
Home-page: UNKNOWN
Author: Parth Tiwari
Author-email: parth@simplyphi.co.uk
License: UNKNOWN
Platform: UNKNOWN
Classifier: Programming Language :: Python :: 3
Classifier: Operating System :: OS Independent
Requires-Python: >=3.9
